tutoraspects_unidigital/__about__.py
tutoraspects_unidigital/__init__.py
tutoraspects_unidigital/plugin.py
tutoraspects_unidigital/patches/.gitignore
tutoraspects_unidigital/patches/superset-extra-asset-translations
tutoraspects_unidigital/patches/superset-extra-assets
tutoraspects_unidigital/templates/aspects-unidigital/apps/.gitignore
tutoraspects_unidigital/templates/aspects-unidigital/build/.gitignore
tutoraspects_unidigital/templates/aspects-unidigital/jobs/init/.gitignore
tutoraspects_unidigital/templates/openedx-assets-unidigital/charts/Course_enrollments_by_mode_352.yaml
tutoraspects_unidigital/templates/openedx-assets-unidigital/charts/Student_status_351.yaml
tutoraspects_unidigital/templates/openedx-assets-unidigital/charts/Total_active_enrollments_338.yaml
tutoraspects_unidigital/templates/openedx-assets-unidigital/charts/Total_active_students_353.yaml
tutoraspects_unidigital/templates/openedx-assets-unidigital/charts/Total_course_enrollments.yaml
tutoraspects_unidigital/templates/openedx-assets-unidigital/charts/Total_courses.yaml
tutoraspects_unidigital/templates/openedx-assets-unidigital/charts/Total_students_339.yaml
tutoraspects_unidigital/templates/openedx-assets-unidigital/charts/Video_count.yaml
tutoraspects_unidigital/templates/openedx-assets-unidigital/dashboards/Aggregation_Dashboard.yaml
tutoraspects_unidigital/templates/openedx-assets-unidigital/dashboards/Professor_Dashboard.yaml
tutoraspects_unidigital/templates/openedx-assets-unidigital/dashboards/Student_Dashboard.yaml
tutoraspects_unidigital/templates/openedx-assets-unidigital/databases/OpenedX_Mysql.yaml
tutoraspects_unidigital/templates/openedx-assets-unidigital/datasets/OpenedX_Mysql/auth_user.yaml
tutoraspects_unidigital/templates/openedx-assets-unidigital/datasets/OpenedX_Mysql/grades_persistentcoursegrade.yaml
tutoraspects_unidigital/templates/openedx-assets-unidigital/datasets/OpenedX_Mysql/student_courseenrollment.yaml
tutor_contrib_aspects_unidigital-0.5.0.dist-info/LICENSE
tutor_contrib_aspects_unidigital-0.5.0.dist-info/METADATA
tutor_contrib_aspects_unidigital-0.5.0.dist-info/WHEEL
tutor_contrib_aspects_unidigital-0.5.0.dist-info/entry_points.txt
tutor_contrib_aspects_unidigital-0.5.0.dist-info/top_level.txt
tutor_contrib_aspects_unidigital-0.5.0.dist-info/RECORD
