Metadata-Version: 2.1
Name: tutor-contrib-aspects-unidigital
Version: 0.5.0
Summary: aspects-unidigital plugin for Tutor
Home-page: https://github.com/eduNEXT/tutor-contrib-aspects-unidigital
Author: Felipe Montoya
License: AGPLv3
Project-URL: Code, https://github.com/eduNEXT/tutor-contrib-aspects-unidigital
Project-URL: Issue tracker, https://github.com/eduNEXT/tutor-contrib-aspects-unidigital/issues
Classifier: Development Status :: 3 - Alpha
Classifier: Intended Audience :: Developers
Classifier: License :: OSI Approved :: GNU Affero General Public License v3
Classifier: Operating System :: OS Independent
Classifier: Programming Language :: Python
Classifier: Programming Language :: Python :: 3.7
Classifier: Programming Language :: Python :: 3.8
Classifier: Programming Language :: Python :: 3.9
Classifier: Programming Language :: Python :: 3.10
Requires-Python: >=3.7
License-File: LICENSE
Requires-Dist: tutor
